hn_data_stock/__init__.py
hn_data_stock/check.py
hn_data_stock/finance_data.py
hn_data_stock/module.py
hn_data_stock/test.py
hn_data_stock/test_finance_data.py
HNDataStock-0.3.4.dist-info/METADATA
HNDataStock-0.3.4.dist-info/WHEEL
HNDataStock-0.3.4.dist-info/top_level.txt
HNDataStock-0.3.4.dist-info/RECORD
