Metadata-Version: 2.1
Name: HNDataStock
Version: 0.3.4
Summary: Trường đào tạo lập trình Ứng dụng, lập trình CSDL, lập trình nhúng, lập trình Forex, Crypto, Chứng Khoán, phân tích dữ liệu
Home-page: http://www.huongnghiepdulieu.com
Author: Hướng Nghiệp Dữ Liệu
Author-email: daotao@huongnghiepdulieu.com
Classifier: Development Status :: 4 - Beta
Classifier: Intended Audience :: Developers
Classifier: Natural Language :: Vietnamese
Classifier: Programming Language :: Python :: 3
Classifier: Programming Language :: Python :: 3.7
Classifier: Programming Language :: Python :: 3.8
Classifier: Programming Language :: Python :: 3.9
Classifier: Topic :: Software Development :: Libraries :: Python Modules
Classifier: License :: OSI Approved :: MIT License
Requires-Dist: requests
Requires-Dist: yfinance
